{
  "posts": [
    {
      "name": "Aman",
      "score": 200,
      "id": 443
    },
    {
      "name": "Aman New",
      "score": 2000,
      "id": 444
    },
    {
      "name": "NewPlayer",
      "score": 120,
      "id": 445
    },
    {
      "name": "Hello1",
      "score": 210,
      "id": 446
    },
    {
      "name": "NewPlayer1",
      "score": 125,
      "id": 447
    },
    {
      "name": "NewPlayer2",
      "score": 130,
      "id": 448
    },
    {
      "name": "Yellow Man",
      "score": 210,
      "id": 449
    },
    {
      "name": "Player1",
      "score": 240,
      "id": 450
    },
    {
      "name": "Player2",
      "score": 470,
      "id": 451
    },
    {
      "name": "",
      "score": 220,
      "id": 452
    },
    {
      "name": "",
      "score": 510,
      "id": 453
    },
    {
      "name": "",
      "score": 0,
      "id": 454
    },
    {
      "name": "",
      "score": 90,
      "id": 455
    },
    {
      "name": "Aman",
      "score": 320,
      "id": 456
    },
    {
      "name": "Winder",
      "score": 220,
      "id": 457
    },
    {
      "name": "Winder",
      "score": 220,
      "id": 458
    },
    {
      "name": "Winder",
      "score": 220,
      "id": 459
    },
    {
      "name": "Winder",
      "score": 220,
      "id": 460
    },
    {
      "name": "Winder",
      "score": 220,
      "id": 461
    },
    {
      "name": "Winder",
      "score": 220,
      "id": 462
    },
    {
      "name": "Winder",
      "score": 220,
      "id": 463
    },
    {
      "name": "Winder",
      "score": 220,
      "id": 464
    },
    {
      "name": "Winder",
      "score": 220,
      "id": 465
    },
    {
      "name": "Winder",
      "score": 220,
      "id": 466
    },
    {
      "name": "Winder",
      "score": 220,
      "id": 467
    },
    {
      "name": "Winder",
      "score": 220,
      "id": 468
    },
    {
      "name": "Winder",
      "score": 220,
      "id": 469
    },
    {
      "name": "Winder",
      "score": 220,
      "id": 470
    },
    {
      "name": "Winder",
      "score": 220,
      "id": 471
    },
    {
      "name": "Winder",
      "score": 220,
      "id": 472
    },
    {
      "name": "Winder",
      "score": 220,
      "id": 473
    },
    {
      "name": "Winder",
      "score": 220,
      "id": 474
    },
    {
      "name": "Winder",
      "score": 220,
      "id": 475
    },
    {
      "name": "Winder",
      "score": 220,
      "id": 476
    },
    {
      "name": "Winder",
      "score": 220,
      "id": 477
    },
    {
      "name": "Winder",
      "score": 220,
      "id": 478
    },
    {
      "name": "Winder",
      "score": 220,
      "id": 479
    },
    {
      "name": "Winder",
      "score": 220,
      "id": 480
    },
    {
      "name": "Winder",
      "score": 220,
      "id": 481
    },
    {
      "name": "Winder",
      "score": 220,
      "id": 482
    },
    {
      "name": "Winder",
      "score": 220,
      "id": 483
    },
    {
      "name": "Winder",
      "score": 220,
      "id": 484
    },
    {
      "name": "Winder",
      "score": 220,
      "id": 485
    },
    {
      "name": "Winder",
      "score": 220,
      "id": 486
    },
    {
      "name": "Winder",
      "score": 220,
      "id": 487
    },
    {
      "name": "Winder",
      "score": 220,
      "id": 488
    },
    {
      "name": "Winder",
      "score": 220,
      "id": 489
    },
    {
      "name": "Winder",
      "score": 220,
      "id": 490
    },
    {
      "name": "Winder",
      "score": 220,
      "id": 491
    },
    {
      "name": "Winder",
      "score": 220,
      "id": 492
    },
    {
      "name": "Winder",
      "score": 220,
      "id": 493
    },
    {
      "name": "Winder",
      "score": 220,
      "id": 494
    },
    {
      "name": "Winder",
      "score": 220,
      "id": 495
    },
    {
      "name": "Winder",
      "score": 220,
      "id": 496
    },
    {
      "name": "Winder",
      "score": 220,
      "id": 497
    },
    {
      "name": "Winder",
      "score": 220,
      "id": 498
    },
    {
      "name": "Winder",
      "score": 220,
      "id": 499
    },
    {
      "name": "Winder",
      "score": 220,
      "id": 500
    },
    {
      "name": "Winder",
      "score": 220,
      "id": 501
    },
    {
      "name": "Winder",
      "score": 220,
      "id": 502
    },
    {
      "name": "Winder",
      "score": 220,
      "id": 503
    },
    {
      "name": "Winder",
      "score": 220,
      "id": 504
    },
    {
      "name": "Winder",
      "score": 220,
      "id": 505
    },
    {
      "name": "Winder",
      "score": 220,
      "id": 506
    },
    {
      "name": "Winder",
      "score": 220,
      "id": 507
    },
    {
      "name": "Winder",
      "score": 220,
      "id": 508
    },
    {
      "name": "Winder",
      "score": 220,
      "id": 509
    },
    {
      "name": "Winder",
      "score": 220,
      "id": 510
    },
    {
      "name": "Winder",
      "score": 220,
      "id": 511
    },
    {
      "name": "Winder",
      "score": 220,
      "id": 512
    },
    {
      "name": "Winder",
      "score": 220,
      "id": 513
    },
    {
      "name": "Winder",
      "score": 220,
      "id": 514
    },
    {
      "name": "Winder",
      "score": 220,
      "id": 515
    },
    {
      "name": "Winder",
      "score": 220,
      "id": 516
    },
    {
      "name": "Winder",
      "score": 220,
      "id": 517
    },
    {
      "name": "Winder",
      "score": 220,
      "id": 518
    },
    {
      "name": "Winder",
      "score": 220,
      "id": 519
    },
    {
      "name": "Winder",
      "score": 220,
      "id": 520
    },
    {
      "name": "Winder",
      "score": 220,
      "id": 521
    },
    {
      "name": "Winder",
      "score": 220,
      "id": 522
    },
    {
      "name": "Winder",
      "score": 220,
      "id": 523
    },
    {
      "name": "Winder",
      "score": 220,
      "id": 524
    },
    {
      "name": "Winder",
      "score": 220,
      "id": 525
    },
    {
      "name": "Winder",
      "score": 220,
      "id": 526
    },
    {
      "name": "Winder",
      "score": 220,
      "id": 527
    },
    {
      "name": "Winder",
      "score": 220,
      "id": 528
    },
    {
      "name": "Winder",
      "score": 220,
      "id": 529
    },
    {
      "name": "Winder",
      "score": 220,
      "id": 530
    },
    {
      "name": "Winder",
      "score": 220,
      "id": 531
    },
    {
      "name": "Winder",
      "score": 220,
      "id": 532
    },
    {
      "name": "Winder",
      "score": 220,
      "id": 533
    },
    {
      "name": "Winder",
      "score": 220,
      "id": 534
    },
    {
      "name": "Winder",
      "score": 220,
      "id": 535
    },
    {
      "name": "Winder",
      "score": 220,
      "id": 536
    },
    {
      "name": "Winder",
      "score": 220,
      "id": 537
    },
    {
      "name": "Winder",
      "score": 220,
      "id": 538
    },
    {
      "name": "Winder",
      "score": 220,
      "id": 539
    },
    {
      "name": "Winder",
      "score": 220,
      "id": 540
    },
    {
      "name": "Winder",
      "score": 220,
      "id": 541
    },
    {
      "name": "Winder",
      "score": 220,
      "id": 542
    },
    {
      "name": "Winder",
      "score": 220,
      "id": 543
    },
    {
      "name": "Winder",
      "score": 220,
      "id": 544
    },
    {
      "name": "Winder",
      "score": 220,
      "id": 545
    },
    {
      "name": "Winder",
      "score": 220,
      "id": 546
    },
    {
      "name": "Winder",
      "score": 220,
      "id": 547
    },
    {
      "name": "Winder",
      "score": 220,
      "id": 548
    },
    {
      "name": "Winder",
      "score": 220,
      "id": 549
    },
    {
      "name": "Winder",
      "score": 220,
      "id": 550
    },
    {
      "name": "Winder",
      "score": 220,
      "id": 551
    },
    {
      "name": "Winder",
      "score": 220,
      "id": 552
    },
    {
      "name": "Winder",
      "score": 220,
      "id": 553
    },
    {
      "name": "Winder",
      "score": 220,
      "id": 554
    },
    {
      "name": "Winder",
      "score": 220,
      "id": 555
    },
    {
      "name": "Winder",
      "score": 220,
      "id": 556
    },
    {
      "name": "Winder",
      "score": 220,
      "id": 557
    },
    {
      "name": "Winder",
      "score": 220,
      "id": 558
    },
    {
      "name": "Winder",
      "score": 220,
      "id": 559
    },
    {
      "name": "Winder",
      "score": 220,
      "id": 560
    },
    {
      "name": "Winder",
      "score": 220,
      "id": 561
    },
    {
      "name": "Winder",
      "score": 220,
      "id": 562
    },
    {
      "name": "Winder",
      "score": 220,
      "id": 563
    },
    {
      "name": "Winder",
      "score": 220,
      "id": 564
    },
    {
      "name": "Winder",
      "score": 220,
      "id": 565
    },
    {
      "name": "Winder",
      "score": 220,
      "id": 566
    },
    {
      "name": "Winder",
      "score": 220,
      "id": 567
    },
    {
      "name": "Winder",
      "score": 220,
      "id": 568
    },
    {
      "name": "Winder",
      "score": 220,
      "id": 569
    },
    {
      "name": "Winder",
      "score": 220,
      "id": 570
    },
    {
      "name": "Winder",
      "score": 220,
      "id": 571
    },
    {
      "name": "Winder",
      "score": 220,
      "id": 572
    },
    {
      "name": "Winder",
      "score": 220,
      "id": 573
    },
    {
      "name": "Winder",
      "score": 220,
      "id": 574
    },
    {
      "name": "Winder",
      "score": 220,
      "id": 575
    },
    {
      "name": "Winder",
      "score": 220,
      "id": 576
    },
    {
      "name": "Winder",
      "score": 220,
      "id": 577
    },
    {
      "name": "Winder",
      "score": 220,
      "id": 578
    },
    {
      "name": "Winder",
      "score": 220,
      "id": 579
    },
    {
      "name": "Winder",
      "score": 220,
      "id": 580
    },
    {
      "name": "Winder",
      "score": 220,
      "id": 581
    },
    {
      "name": "Winder",
      "score": 220,
      "id": 582
    },
    {
      "name": "Winder",
      "score": 220,
      "id": 583
    },
    {
      "name": "Winder",
      "score": 220,
      "id": 584
    },
    {
      "name": "Winder",
      "score": 220,
      "id": 585
    },
    {
      "name": "Winder",
      "score": 220,
      "id": 586
    },
    {
      "name": "Winder",
      "score": 220,
      "id": 587
    },
    {
      "name": "Winder",
      "score": 220,
      "id": 588
    },
    {
      "name": "Winder",
      "score": 220,
      "id": 589
    },
    {
      "name": "Winder",
      "score": 220,
      "id": 590
    },
    {
      "name": "Winder",
      "score": 220,
      "id": 591
    },
    {
      "name": "Winder",
      "score": 220,
      "id": 592
    },
    {
      "name": "Winder",
      "score": 220,
      "id": 593
    },
    {
      "name": "Winder",
      "score": 220,
      "id": 594
    },
    {
      "name": "Winder",
      "score": 220,
      "id": 595
    },
    {
      "name": "Winder",
      "score": 220,
      "id": 596
    },
    {
      "name": "Winder",
      "score": 220,
      "id": 597
    },
    {
      "name": "Winder",
      "score": 220,
      "id": 598
    },
    {
      "name": "Winder",
      "score": 220,
      "id": 599
    },
    {
      "name": "Winder",
      "score": 220,
      "id": 600
    },
    {
      "name": "Winder",
      "score": 220,
      "id": 601
    },
    {
      "name": "Winder",
      "score": 220,
      "id": 602
    },
    {
      "name": "Winder",
      "score": 220,
      "id": 603
    },
    {
      "name": "Winder",
      "score": 220,
      "id": 604
    },
    {
      "name": "Winder",
      "score": 220,
      "id": 605
    },
    {
      "name": "Winder",
      "score": 220,
      "id": 606
    },
    {
      "name": "Winder",
      "score": 220,
      "id": 607
    },
    {
      "name": "Winder",
      "score": 220,
      "id": 608
    },
    {
      "name": "Winder",
      "score": 220,
      "id": 609
    },
    {
      "name": "Winder",
      "score": 220,
      "id": 610
    },
    {
      "name": "Winder",
      "score": 220,
      "id": 611
    },
    {
      "name": "Winder",
      "score": 220,
      "id": 612
    },
    {
      "name": "Winder",
      "score": 220,
      "id": 613
    },
    {
      "name": "Winder",
      "score": 220,
      "id": 614
    },
    {
      "name": "Winder",
      "score": 220,
      "id": 615
    },
    {
      "name": "Winder",
      "score": 220,
      "id": 616
    },
    {
      "name": "Winder",
      "score": 220,
      "id": 617
    },
    {
      "name": "Winder",
      "score": 220,
      "id": 618
    },
    {
      "name": "Winder",
      "score": 220,
      "id": 619
    },
    {
      "name": "Winder",
      "score": 220,
      "id": 620
    },
    {
      "name": "Winder",
      "score": 220,
      "id": 621
    },
    {
      "name": "Winder",
      "score": 220,
      "id": 622
    },
    {
      "name": "Winder",
      "score": 220,
      "id": 623
    },
    {
      "name": "Winder",
      "score": 220,
      "id": 624
    },
    {
      "name": "Winder",
      "score": 220,
      "id": 625
    },
    {
      "name": "Winder",
      "score": 220,
      "id": 626
    },
    {
      "name": "Winder",
      "score": 220,
      "id": 627
    },
    {
      "name": "Winder",
      "score": 220,
      "id": 628
    },
    {
      "name": "Winder",
      "score": 220,
      "id": 629
    },
    {
      "name": "Winder",
      "score": 220,
      "id": 630
    },
    {
      "name": "Winder",
      "score": 220,
      "id": 631
    },
    {
      "name": "Winder",
      "score": 220,
      "id": 632
    },
    {
      "name": "Winder",
      "score": 220,
      "id": 633
    },
    {
      "name": "Winder",
      "score": 220,
      "id": 634
    },
    {
      "name": "Winder",
      "score": 220,
      "id": 635
    },
    {
      "name": "Winder",
      "score": 220,
      "id": 636
    },
    {
      "name": "Winder",
      "score": 220,
      "id": 637
    },
    {
      "name": "Winder",
      "score": 220,
      "id": 638
    },
    {
      "name": "Winder",
      "score": 220,
      "id": 639
    },
    {
      "name": "Winder",
      "score": 220,
      "id": 640
    },
    {
      "name": "Winder",
      "score": 220,
      "id": 641
    },
    {
      "name": "Winder",
      "score": 220,
      "id": 642
    },
    {
      "name": "Winder",
      "score": 220,
      "id": 643
    },
    {
      "name": "Winder",
      "score": 220,
      "id": 644
    },
    {
      "name": "Winder",
      "score": 220,
      "id": 645
    },
    {
      "name": "Winder",
      "score": 220,
      "id": 646
    },
    {
      "name": "Winder",
      "score": 220,
      "id": 647
    },
    {
      "name": "Winder",
      "score": 220,
      "id": 648
    },
    {
      "name": "Winder",
      "score": 220,
      "id": 649
    },
    {
      "name": "Winder",
      "score": 220,
      "id": 650
    },
    {
      "name": "Winder",
      "score": 220,
      "id": 651
    },
    {
      "name": "Winder",
      "score": 220,
      "id": 652
    },
    {
      "name": "Winder",
      "score": 220,
      "id": 653
    },
    {
      "name": "Winder",
      "score": 220,
      "id": 654
    },
    {
      "name": "Winder",
      "score": 220,
      "id": 655
    },
    {
      "name": "Winder",
      "score": 220,
      "id": 656
    },
    {
      "name": "Winder",
      "score": 220,
      "id": 657
    },
    {
      "name": "Winder",
      "score": 220,
      "id": 658
    },
    {
      "name": "Winder",
      "score": 220,
      "id": 659
    },
    {
      "name": "Winder",
      "score": 220,
      "id": 660
    },
    {
      "name": "Winder",
      "score": 220,
      "id": 661
    },
    {
      "name": "Winder",
      "score": 220,
      "id": 662
    },
    {
      "name": "Winder",
      "score": 220,
      "id": 663
    },
    {
      "name": "Winder",
      "score": 220,
      "id": 664
    },
    {
      "name": "Winder",
      "score": 220,
      "id": 665
    },
    {
      "name": "Winder",
      "score": 220,
      "id": 666
    },
    {
      "name": "Winder",
      "score": 220,
      "id": 667
    },
    {
      "name": "Winder",
      "score": 220,
      "id": 668
    },
    {
      "name": "Winder",
      "score": 220,
      "id": 669
    },
    {
      "name": "Winder",
      "score": 220,
      "id": 670
    },
    {
      "name": "Winder",
      "score": 220,
      "id": 671
    },
    {
      "name": "Winder",
      "score": 220,
      "id": 672
    },
    {
      "name": "Winder",
      "score": 220,
      "id": 673
    },
    {
      "name": "Winder",
      "score": 220,
      "id": 674
    },
    {
      "name": "Winder",
      "score": 220,
      "id": 675
    },
    {
      "name": "Winder",
      "score": 220,
      "id": 676
    },
    {
      "name": "Winder",
      "score": 220,
      "id": 677
    },
    {
      "name": "Winder",
      "score": 220,
      "id": 678
    },
    {
      "name": "Winder",
      "score": 220,
      "id": 679
    },
    {
      "name": "Winder",
      "score": 220,
      "id": 680
    },
    {
      "name": "Winder",
      "score": 220,
      "id": 681
    },
    {
      "name": "Winder",
      "score": 220,
      "id": 682
    },
    {
      "name": "Winder",
      "score": 220,
      "id": 683
    },
    {
      "name": "Winder",
      "score": 220,
      "id": 684
    },
    {
      "name": "Winder",
      "score": 220,
      "id": 685
    },
    {
      "name": "Winder",
      "score": 220,
      "id": 686
    },
    {
      "name": "Winder",
      "score": 220,
      "id": 687
    },
    {
      "name": "Winder",
      "score": 220,
      "id": 688
    },
    {
      "name": "Winder",
      "score": 220,
      "id": 689
    },
    {
      "name": "Winder",
      "score": 220,
      "id": 690
    },
    {
      "name": "Winder",
      "score": 220,
      "id": 691
    },
    {
      "name": "Winder",
      "score": 220,
      "id": 692
    },
    {
      "name": "Winder",
      "score": 220,
      "id": 693
    },
    {
      "name": "Winder",
      "score": 220,
      "id": 694
    },
    {
      "name": "Winder",
      "score": 220,
      "id": 695
    },
    {
      "name": "Winder",
      "score": 220,
      "id": 696
    },
    {
      "name": "Winder",
      "score": 220,
      "id": 697
    },
    {
      "name": "Winder",
      "score": 220,
      "id": 698
    },
    {
      "name": "Winder",
      "score": 220,
      "id": 699
    },
    {
      "name": "Winder",
      "score": 220,
      "id": 700
    },
    {
      "name": "Winder",
      "score": 220,
      "id": 701
    },
    {
      "name": "Winder",
      "score": 220,
      "id": 702
    },
    {
      "name": "Winder",
      "score": 220,
      "id": 703
    },
    {
      "name": "Winder",
      "score": 220,
      "id": 704
    },
    {
      "name": "Winder",
      "score": 220,
      "id": 705
    },
    {
      "name": "Winder",
      "score": 220,
      "id": 706
    },
    {
      "name": "Winder",
      "score": 220,
      "id": 707
    },
    {
      "name": "Winder",
      "score": 220,
      "id": 708
    },
    {
      "name": "Winder",
      "score": 220,
      "id": 709
    },
    {
      "name": "Winder",
      "score": 220,
      "id": 710
    },
    {
      "name": "Winder",
      "score": 220,
      "id": 711
    },
    {
      "name": "Winder",
      "score": 220,
      "id": 712
    },
    {
      "name": "Winder",
      "score": 220,
      "id": 713
    },
    {
      "name": "Winder",
      "score": 220,
      "id": 714
    },
    {
      "name": "Winder",
      "score": 220,
      "id": 715
    },
    {
      "name": "Winder",
      "score": 220,
      "id": 716
    },
    {
      "name": "Winder",
      "score": 220,
      "id": 717
    },
    {
      "name": "Winder",
      "score": 220,
      "id": 718
    },
    {
      "name": "Winder",
      "score": 220,
      "id": 719
    },
    {
      "name": "Winder",
      "score": 220,
      "id": 720
    },
    {
      "name": "Winder",
      "score": 220,
      "id": 721
    },
    {
      "name": "Winder",
      "score": 220,
      "id": 722
    },
    {
      "name": "Winder",
      "score": 220,
      "id": 723
    },
    {
      "name": "Winder",
      "score": 220,
      "id": 724
    },
    {
      "name": "Winder",
      "score": 220,
      "id": 725
    },
    {
      "name": "Winder",
      "score": 220,
      "id": 726
    },
    {
      "name": "Winder",
      "score": 220,
      "id": 727
    },
    {
      "name": "Winder",
      "score": 220,
      "id": 728
    },
    {
      "name": "Winder",
      "score": 220,
      "id": 729
    },
    {
      "name": "Winder",
      "score": 220,
      "id": 730
    },
    {
      "name": "Winder",
      "score": 220,
      "id": 731
    },
    {
      "name": "Winder",
      "score": 220,
      "id": 732
    },
    {
      "name": "Winder",
      "score": 220,
      "id": 733
    },
    {
      "name": "Winder",
      "score": 220,
      "id": 734
    },
    {
      "name": "Winder",
      "score": 220,
      "id": 735
    },
    {
      "name": "Winder",
      "score": 220,
      "id": 736
    },
    {
      "name": "Winder",
      "score": 220,
      "id": 737
    },
    {
      "name": "Winder",
      "score": 220,
      "id": 738
    },
    {
      "name": "Winder",
      "score": 220,
      "id": 739
    },
    {
      "name": "Winder",
      "score": 220,
      "id": 740
    },
    {
      "name": "Winder",
      "score": 220,
      "id": 741
    },
    {
      "name": "Winder",
      "score": 220,
      "id": 742
    },
    {
      "name": "Winder",
      "score": 220,
      "id": 743
    },
    {
      "name": "Winder",
      "score": 220,
      "id": 744
    },
    {
      "name": "Winder",
      "score": 220,
      "id": 745
    },
    {
      "name": "Winder",
      "score": 220,
      "id": 746
    },
    {
      "name": "Winder",
      "score": 220,
      "id": 747
    },
    {
      "name": "Winder",
      "score": 220,
      "id": 748
    },
    {
      "name": "Winder",
      "score": 220,
      "id": 749
    },
    {
      "name": "Winder",
      "score": 220,
      "id": 750
    },
    {
      "name": "Winder",
      "score": 220,
      "id": 751
    },
    {
      "name": "Winder",
      "score": 220,
      "id": 752
    },
    {
      "name": "Winder",
      "score": 220,
      "id": 753
    },
    {
      "name": "Winder",
      "score": 220,
      "id": 754
    },
    {
      "name": "Winder",
      "score": 220,
      "id": 755
    },
    {
      "name": "Winder",
      "score": 220,
      "id": 756
    },
    {
      "name": "Winder",
      "score": 220,
      "id": 757
    },
    {
      "name": "Winder",
      "score": 220,
      "id": 758
    },
    {
      "name": "Winder",
      "score": 220,
      "id": 759
    },
    {
      "name": "Winder",
      "score": 220,
      "id": 760
    },
    {
      "name": "Winder",
      "score": 220,
      "id": 761
    },
    {
      "name": "Winder",
      "score": 220,
      "id": 762
    },
    {
      "name": "Winder",
      "score": 220,
      "id": 763
    },
    {
      "name": "Winder",
      "score": 220,
      "id": 764
    },
    {
      "name": "Winder",
      "score": 220,
      "id": 765
    },
    {
      "name": "Winder",
      "score": 220,
      "id": 766
    },
    {
      "name": "Winder",
      "score": 220,
      "id": 767
    },
    {
      "name": "Winder",
      "score": 220,
      "id": 768
    },
    {
      "name": "Winder",
      "score": 220,
      "id": 769
    },
    {
      "name": "Winder",
      "score": 220,
      "id": 770
    },
    {
      "name": "Winder",
      "score": 220,
      "id": 771
    },
    {
      "name": "Winder",
      "score": 220,
      "id": 772
    },
    {
      "name": "Winder",
      "score": 220,
      "id": 773
    },
    {
      "name": "Winder",
      "score": 220,
      "id": 774
    }
  ],
  "comments": [
    {
      "id": 1,
      "body": "some comment",
      "postId": 1
    }
  ],
  "profile": {
    "name": "typicode"
  }
}